prior/__init__.py
prior/lock.py
prior/py.typed
prior/version.py
prior/utils/__init__.py
prior/utils/types.py
prior-1.0.3.dist-info/LICENSE
prior-1.0.3.dist-info/METADATA
prior-1.0.3.dist-info/WHEEL
prior-1.0.3.dist-info/top_level.txt
prior-1.0.3.dist-info/RECORD
